YamlStripper/__init__.py
YamlStripper/cli.py
YamlStripper/yaml_stripper.py
test/__init__.py
test/test_yaml_stripper.py
yaml_stripper-2.1.2.dist-info/METADATA
yaml_stripper-2.1.2.dist-info/WHEEL
yaml_stripper-2.1.2.dist-info/entry_points.txt
yaml_stripper-2.1.2.dist-info/top_level.txt
yaml_stripper-2.1.2.dist-info/RECORD
