Metadata-Version: 2.1
Name: yaml-stripper
Version: 2.1.2
Summary: A command-line tool for removing specified fields from YAML files.
Home-page: https://github.com/vavasilva/yaml-stripper
Author: Wagner Silva
Author-email: wra.silva@gmail.com
Project-URL: Bug Tracker, https://github.com/vavasilva/YamlStripper
Project-URL: Documentation, https://github.com/vavasilva/YamlStripper
Project-URL: Source Code, https://github.com/vavasilva/YamlStripper
Project-URL: Homepage, https://github.com/vavasilva/YamlStripper
Classifier: Programming Language :: Python :: 3
Classifier: License :: OSI Approved :: MIT License
Classifier: Operating System :: OS Independent
Requires-Python: >=3.6
Requires-Dist: PyYAML (>=6.0)
Requires-Dist: click (>=8.1.3)
Requires-Dist: keyring
